verden_pa_norsk/__init__.py
verden_pa_norsk/config.cfg
verden_pa_norsk/mongodb.py
verden_pa_norsk/streamlit_tools.py
verden_pa_norsk-0.1.0.dist-info/METADATA
verden_pa_norsk-0.1.0.dist-info/WHEEL
verden_pa_norsk-0.1.0.dist-info/RECORD
