Metadata-Version: 2.1
Name: verden-pa-norsk
Version: 0.1.0
Summary: 
Author: Lars Magne Tungland
Author-email: larsmtungland@gmail.com
Requires-Python: >=3.10,<4.0
Classifier: Programming Language :: Python :: 3
Classifier: Programming Language :: Python :: 3.10
Classifier: Programming Language :: Python :: 3.11
Requires-Dist: black[jupyter] (>=23.7.0,<24.0.0)
Requires-Dist: dhlab (==3.0.0a6)
Requires-Dist: duckdb (>=0.9.1,<0.10.0)
Requires-Dist: folium (>=0.13,<0.15)
Requires-Dist: geopy (>=2.4.1,<3.0.0)
Requires-Dist: jupyter (>=1.0.0,<2.0.0)
Requires-Dist: lxml (>=4.9.3,<5.0.0)
Requires-Dist: openpyxl (>=3.1.2,<4.0.0)
Requires-Dist: pandas (>=2.0.3,<3.0.0)
Requires-Dist: pyarrow (>=12.0.1,<13.0.0)
Requires-Dist: pymarc (>=5.1.0,<6.0.0)
Requires-Dist: pymongo (>=4.4.1,<5.0.0)
Requires-Dist: rdflib (>=7.0.0,<8.0.0)
Requires-Dist: requests (>=2.31.0,<3.0.0)
Requires-Dist: sparqlwrapper (>=2.0.0,<3.0.0)
Requires-Dist: streamlit (>=1.27.2,<2.0.0)
Requires-Dist: streamlit-folium (>=0.16.0,<0.17.0)
Requires-Dist: tqdm (>=4.65.0,<5.0.0)
